pycrypto_helper/__init__.py
pycrypto_helper/crypto_helper.py
pycrypto_helper-0.2.0.dist-info/LICENSE
pycrypto_helper-0.2.0.dist-info/METADATA
pycrypto_helper-0.2.0.dist-info/WHEEL
pycrypto_helper-0.2.0.dist-info/top_level.txt
pycrypto_helper-0.2.0.dist-info/RECORD
