Metadata-Version: 2.1
Name: pycrypto-helper
Version: 0.2.0
Summary: A helper library for cryptographic operations
Home-page: https://github.com/embetrix/pycrypto-helper
Author: Embetrix
Author-email: info@embetrix.com
Classifier: Programming Language :: Python :: 3
Classifier: License :: OSI Approved :: MIT License
Classifier: Operating System :: OS Independent
Requires-Python: >=3.6
License-File: LICENSE
Requires-Dist: asn1crypto
Requires-Dist: pycryptodomex
Requires-Dist: python-pkcs11
